bulkhead/__init__.py
bulkhead/base_interface.py
bulkhead/endpoint/__init__.py
bulkhead/endpoint/interface.py
bulkhead/endpoint/weather_endpoint.py
bulkhead/endpoint_collection/__init__.py
bulkhead/endpoint_collection/endpoint_collection.py
bulkhead/endpoint_collection/interface.py
bulkhead/sampler/__init__.py
bulkhead/sampler/interface.py
bulkhead/sampler/sampler.py
bulkhead/utils/__init__.py
bulkhead/utils/file_utils.py
bulkhead-0.1.5.dist-info/LICENSE
bulkhead-0.1.5.dist-info/METADATA
bulkhead-0.1.5.dist-info/WHEEL
bulkhead-0.1.5.dist-info/top_level.txt
bulkhead-0.1.5.dist-info/RECORD
