Metadata-Version: 2.1
Name: bulkhead
Version: 0.1.5
Summary: package providing objects for API interaction
Home-page: http://www.codeberg/cap_jmk/prettify-py
Author: Julian M. Kleber
Author-email: julian.m.kleber@gmail.com
Classifier: Programming Language :: Python :: 3
Classifier: License :: OSI Approved :: GNU General Public License v3 (GPLv3)
Classifier: Operating System :: OS Independent
Requires-Python: >=3.9
License-File: LICENSE
Requires-Dist: python-dotenv
